{
    "id": "shaffi",
    "title": "مشروع مدرسة الشافعيّ لرعاية الطفولة – للبنين",
    "type":"formal-education",
    "description": "الأطفال الأيتام في مرحلة التعليم الأساسيّ",
    "slug": "al-shafii-school-for-boys",
    "fullDescription": "\nأُطلقت مدرسة الشافعيّ لرعاية الطفولة (للبنين) في مدينة الأتارب عام 2015 كمبادرة تعليميّة وإنسانيّة متخصّصة في رعاية وتأهيل الأطفال الأيتام وأبناء الشهداء تربويًّا ونفسيًّا واجتماعيًّا. تعمل المدرسة ضمن مبنى حكوميّ تمّت إعادة ترميمه، وتستقبل اليوم أكثر من 700 طالب، ويشرف عليهم كادر تربويّ وإداريّ مكوّن من نحو 36 موظّفًا. وتوفّر المدرسة بيئة تعليميّة آمنة ومتكاملة، تُعنى بالجانب الأكاديميّ والنفسيّ والقيميّ للطفل.\n      ",
    "importance": "\nيُعد المشروع مبادرة رائدة لدعم الأطفال الأيتام في بيئات الصراع، حيث يعزز تحصيلهم العلمي واندماجهم المجتمعي. ويوفر بيئة تربوية آمنة تخفف من آثار الحرب والحرمان.\n      ",
    "importanceList": [
      "ساهم المشروع في رفع مستوى التحصيل العلميّ وتعزيز السلوك القيميّ لدى الأطفال، خاصة الأيتام منهم.",
      "وفّر بيئة تربوية حاضنة خفّفت من آثار الفقد والحرمان التي خلفتها ظروف الحرب.",
      "عمل على تعزيز اندماج الأطفال في المجتمع من خلال أنشطة شاملة وداعمة.",
      "مثّل نموذجًا ناجحًا للتعليم الإنساني في البيئات المتأثرة بالصراع طويل الأمد."
    ],
    "components": [
      {
        "title": "• التعليم والتأهيل الأكاديميّ:",
        "description": "منهج رسميّ مرن يُراعي الفروق الفرديّة، وبناء خطط علاجيّة جماعيّة وفرديّة، وتعزيز العلاقة التربويّة بين المعلّمين والطلاب في بيئة تعليمية مشجّعة."
      },
      {
        "title": "• الرعاية الصحّيّة والغذائيّة: ",
        "description": "تقديم وجبات مغذّية، وتنظيم فحوصات طبّيّة دوريّة، وجلسات توعية صحّيّة، والحفاظ على بيئة نظيفة وآمنة تعزّز الصحة الجسديّة والنفسيّة."
      },
      {
        "title": "• الدعم النفسيّ والحماية:  ",
        "description": "جلسات دعم نفسي فرديّة وجماعيّة بإشراف مختصّين، وتدريبات للمعلمين، وخلق بيئة خالية من العنف والتمييز، توفّر الأمان والدعم للأطفال."
      },
      {
        "title": "• التربية السلوكيّة وغرس القيم: ",
        "description": "برامج تربويّة تفاعلية تُعزّز السلوك الإيجابيّ والانضباط الذاتيّ، وأنشطة لا منهجيّة تغرس القيم الأخلاقية وتعزّز المسؤوليّة الاجتماعيّة."
      },
      {
        "title": "• الأنشطة المهاريّة والتربويّة: ",
        "description": "تنظيم أنشطة فنّيّة وزراعيّة ورياضيّة، مع إقامة معارض ومهرجانات دوريّة لعرض مواهب الطلاب وتنمية روح المبادرة لديهم."
      },
      {
        "title": "• الدعم اللوجستيّ: ",
        "description": "توفير النقل المجّاني للأطفال الأيتام، وتأمين المستلزمات الدراسيّة، وتوفير الملابس، والتدفئة، وإجراء صيانة دوريّة للمرافق تضمن استدامة البيئة المدرسيّة."
      }
    ],
    "image": "https://res.cloudinary.com/dokawmydv/image/upload/v1762079001/3_t1fr6m.jpg",
    "gallery": [
      "https://res.cloudinary.com/dokawmydv/image/upload/v1762079025/84844_gauf6d.jpg",
      "https://res.cloudinary.com/dokawmydv/image/upload/v1762079047/Untitled1_b0unmx.jpg",
      "https://res.cloudinary.com/dokawmydv/image/upload/v1764839573/502578207_1317227246949976_7858246798083983432_n_lezrgl.jpg"
       
    ],
    "videoUrl": "https://www.youtube.com/embed/dQw4w9WgXcQ",
    "location": "سوريا - ريف حلب - الأتارب",
    "beneficiaries": 700,
    "status": "in-progress",
    "startDate": "2015-01-15",
    "endDate": "",
    "budget": 0,
    "partners": [
      "المشيخة الإسلامية في البوسنة والهرسك",
      "وزارة التربية والتعليم"
    ],
    "objectives": [
      "تقديم تعليم نوعي وآمن للأطفال الذكور الأيتام وأبناء الشهداء",
      "ردم الفجوة التعليميّة من خلال برامج استدراكيّة تراعي الحالة النفسيّة والتربوية لليتيم.",
      "دعم النموّ النفسيّ والاجتماعيّ للأطفال ومساعدتهم على تجاوز آثار الصدمة.",
      "تنمية القيم الأخلاقيّة والانضباط السلوكيّ لدى الطلاب.",
      "اكتشاف مواهب الأطفال وصقلها في مختلف المجالات.",
      "تحفيز التفاعل المجتمعيّ وتوسيع شبكة الدعم المحليّ لرعاية الأيتام."
    ],
    "statistics": {
      "schoolsRenovated": [
        {
          "month": "يناير",
          "count": 0
        },
        {
          "month": "فبراير",
          "count": 1
        },
        {
          "month": "مارس",
          "count": 2
        },
        {
          "month": "أبريل",
          "count": 3
        },
        {
          "month": "مايو",
          "count": 4
        },
        {
          "month": "يونيو",
          "count": 6
        },
        {
          "month": "يوليو",
          "count": 8
        }
      ],
      "budgetDistribution": [
        {
          "name": "إصلاحات هيكلية",
          "value": 35
        },
        {
          "name": "تجهيزات مدرسية",
          "value": 25
        },
        {
          "name": "مرافق صحية",
          "value": 15
        },
        {
          "name": "وسائل تعليمية",
          "value": 15
        },
        {
          "name": "مساحات ترفيهية",
          "value": 10
        }
      ],
      "impactMetrics": {
        "enrollmentIncrease": 28,
        "dropoutReduction": 45,
        "academicPerformance": 32,
        "teacherSatisfaction": 85
      }
    }
  }